protectedblob
