Metadata-Version: 1.1
Name: protectedblob
Version: 0.9.5
Summary: Create passphrase-protected blobs
Home-page: https://github.com/lukhnos/protectedblob-py
Author: Lukhnos Liu
Author-email: lukhnos@lukhnos.org
License: MIT
Platform: UNKNOWN
Classifier: Development Status :: 4 - Beta
Classifier: Environment :: Console
Classifier: Intended Audience :: Developers
Classifier: Intended Audience :: Education
Classifier: Intended Audience :: System Administrators
Classifier: License :: OSI Approved :: MIT License
Classifier: Operating System :: Unix
Classifier: Programming Language :: Python :: 2
Classifier: Programming Language :: Python :: 3
Classifier: Topic :: Security :: Cryptography
